pip_toolbox/__init__.py
pip_toolbox/main.py
pip_toolbox-0.4.5.dist-info/METADATA
pip_toolbox-0.4.5.dist-info/WHEEL
pip_toolbox-0.4.5.dist-info/entry_points.txt
pip_toolbox-0.4.5.dist-info/top_level.txt
pip_toolbox-0.4.5.dist-info/RECORD
