Metadata-Version: 2.4
Name: pip-toolbox
Version: 0.4.5
Summary: A toolbox for managing Python packages
Author: lilys
Author-email: lysder@qq.com
Requires-Dist: tk
Dynamic: author
Dynamic: author-email
Dynamic: description
Dynamic: description-content-type
Dynamic: requires-dist
Dynamic: summary
